Metadata-Version: 2.1
Name: snowflake-snowpark-python3
Version: 1.0.0
Summary: Snowflake Snowpark for Python
Home-page: https://www.snowflake.com/
Author: Snowflake, Inc
Author-email: snowflake-python-libraries-dl@snowflake.com
License: Apache License, Version 2.0
Project-URL: Documentation, https://docs.snowflake.com/en/developer-guide/snowpark/python/index.html
Project-URL: Source, https://github.com/snowflakedb/snowpark-python
Project-URL: Issues, https://github.com/snowflakedb/snowpark-python/issues
Project-URL: Changelog, https://github.com/snowflakedb/snowpark-python/blob/main/CHANGELOG.md
Keywords: Snowflake db database cloud analytics warehouse
Classifier: Development Status :: 5 - Production/Stable
Classifier: Environment :: Console
Classifier: Environment :: Other Environment
Classifier: Intended Audience :: Developers
Classifier: Intended Audience :: Education
Classifier: Intended Audience :: Information Technology
Classifier: Intended Audience :: System Administrators
Classifier: License :: OSI Approved :: Apache Software License
Classifier: Operating System :: OS Independent
Classifier: Programming Language :: SQL
Classifier: Programming Language :: Python :: 3 :: Only
Classifier: Programming Language :: Python :: 3.8
Classifier: Programming Language :: Python :: 3.9
Classifier: Programming Language :: Python :: 3.10
Classifier: Topic :: Database
Classifier: Topic :: Software Development
Classifier: Topic :: Software Development :: Libraries
Classifier: Topic :: Software Development :: Libraries :: Application Frameworks
Classifier: Topic :: Software Development :: Libraries :: Python Modules
Classifier: Topic :: Scientific/Engineering :: Information Analysis
Requires-Python: >=3.8
License-File: LICENSE.txt
Requires-Dist: setuptools (>=40.6.0)
Requires-Dist: wheel
Requires-Dist: cloudpickle (<=2.0.0,>=1.6.0)
Requires-Dist: snowflake-connector-python (<3.0.0,>=2.7.12)
Requires-Dist: typing-extensions (<5.0.0,>=4.1.0)
Provides-Extra: development
Requires-Dist: pytest ; extra == 'development'
Requires-Dist: pytest-cov ; extra == 'development'
Requires-Dist: coverage ; extra == 'development'
Requires-Dist: sphinx (==5.0.2) ; extra == 'development'
Requires-Dist: cachetools ; extra == 'development'
Provides-Extra: pandas
Requires-Dist: snowflake-connector-python[pandas] (<3.0.0,>=2.7.12) ; extra == 'pandas'
Provides-Extra: secure-local-storage
Requires-Dist: snowflake-connector-python[secure-local-storage] (<3.0.0,>=2.7.12) ; extra == 'secure-local-storage'
